pysnail/__init__.py
pysnail/__main__.py
pysnail/py.typed
pysnail/pysnail.py
pysnail-0.0.4.dist-info/METADATA
pysnail-0.0.4.dist-info/WHEEL
pysnail-0.0.4.dist-info/licenses/LICENSE
pysnail-0.0.4.dist-info/RECORD
